AMPcombi-2.0.1.data/scripts/amp_database.py
AMPcombi-2.0.1.data/scripts/amp_fasta.py
AMPcombi-2.0.1.data/scripts/ampcombi.py
AMPcombi-2.0.1.data/scripts/check_input.py
AMPcombi-2.0.1.data/scripts/clustering_hits.py
AMPcombi-2.0.1.data/scripts/complete_summary.py
AMPcombi-2.0.1.data/scripts/functionality.py
AMPcombi-2.0.1.data/scripts/hmm_to_csv_input_file.py
AMPcombi-2.0.1.data/scripts/optional_inputs.py
AMPcombi-2.0.1.data/scripts/parse_gbks.py
AMPcombi-2.0.1.data/scripts/print_header.py
AMPcombi-2.0.1.data/scripts/reformat_tables.py
AMPcombi-2.0.1.data/scripts/signalpep_pred.py
AMPcombi-2.0.1.data/scripts/version.py
ampcombi/__init__.py
ampcombi/amp_database.py
ampcombi/amp_fasta.py
ampcombi/ampcombi.py
ampcombi/check_input.py
ampcombi/clustering_hits.py
ampcombi/complete_summary.py
ampcombi/functionality.py
ampcombi/hmm_to_csv_input_file.py
ampcombi/optional_inputs.py
ampcombi/parse_gbks.py
ampcombi/print_header.py
ampcombi/reformat_tables.py
ampcombi/signalpep_pred.py
ampcombi/version.py
AMPcombi-2.0.1.dist-info/LICENSE.txt
AMPcombi-2.0.1.dist-info/METADATA
AMPcombi-2.0.1.dist-info/WHEEL
AMPcombi-2.0.1.dist-info/entry_points.txt
AMPcombi-2.0.1.dist-info/top_level.txt
AMPcombi-2.0.1.dist-info/RECORD
