Metadata-Version: 2.1
Name: AMPcombi
Version: 2.0.1
Summary: A parsing tool for AMP tools.
Home-page: http://pypi.python.org/pypi/AMPcombi/
Author: Anan Ibrahim, Louisa Perelo
Author-email: ananhamido@hotmail.com, louperelo@gmail.com
License: LICENSE.txt
Keywords: Proteomics,Antimicrobial peptides,MMSeqs2Standardization,Formatting,Functional annotation
Classifier: Development Status :: 4 - Beta
Classifier: Environment :: Console
Classifier: License :: OSI Approved :: MIT License
Classifier: Natural Language :: English
Classifier: Operating System :: MacOS
Classifier: Operating System :: POSIX
Classifier: Operating System :: POSIX :: Linux
Classifier: Programming Language :: Python :: 3.11
Classifier: Intended Audience :: Science/Research
Classifier: Intended Audience :: Healthcare Industry
Classifier: Topic :: Scientific/Engineering :: Bio-Informatics
Classifier: Topic :: Scientific/Engineering :: Information Analysis
Requires-Python: ==3.11.*
License-File: LICENSE.txt
Requires-Dist: pandas ==1.5.2
Requires-Dist: numpy ==1.26.4
Requires-Dist: biopython ==1.80
Requires-Dist: colorama ==0.4.6
Requires-Dist: requests
